openassessment/__init__.py
openassessment/data.py
openassessment/test_utils.py
openassessment/assessment/__init__.py
openassessment/assessment/admin.py
openassessment/assessment/data_conversion.py
openassessment/assessment/score_type_constants.py
openassessment/assessment/signals.py
openassessment/assessment/urls.py
openassessment/assessment/views.py
openassessment/assessment/api/__init__.py
openassessment/assessment/api/peer.py
openassessment/assessment/api/self.py
openassessment/assessment/api/staff.py
openassessment/assessment/api/student_training.py
openassessment/assessment/api/teams.py
openassessment/assessment/errors/__init__.py
openassessment/assessment/errors/base.py
openassessment/assessment/errors/peer.py
openassessment/assessment/errors/self.py
openassessment/assessment/errors/staff.py
openassessment/assessment/errors/student_training.py
openassessment/assessment/migrations/0001_initial.py
openassessment/assessment/migrations/0002_staffworkflow.py
openassessment/assessment/migrations/0003_expand_course_id.py
openassessment/assessment/migrations/0004_historicalsharedfileupload_sharedfileupload.py
openassessment/assessment/migrations/0005_add_filename_to_sharedupload.py
openassessment/assessment/migrations/0006_TeamWorkflows.py
openassessment/assessment/migrations/0007_staff_workflow_blank.py
openassessment/assessment/migrations/0008_alter_historicalsharedfileupload_options.py
openassessment/assessment/migrations/__init__.py
openassessment/assessment/models/__init__.py
openassessment/assessment/models/base.py
openassessment/assessment/models/peer.py
openassessment/assessment/models/staff.py
openassessment/assessment/models/student_training.py
openassessment/assessment/models/training.py
openassessment/assessment/serializers/__init__.py
openassessment/assessment/serializers/base.py
openassessment/assessment/serializers/peer.py
openassessment/assessment/serializers/training.py
openassessment/fileupload/__init__.py
openassessment/fileupload/api.py
funixora2-0.2.1.dist-info/LICENSE
funixora2-0.2.1.dist-info/METADATA
funixora2-0.2.1.dist-info/WHEEL
funixora2-0.2.1.dist-info/entry_points.txt
funixora2-0.2.1.dist-info/top_level.txt
funixora2-0.2.1.dist-info/RECORD
