Metadata-Version: 2.1
Name: funixora2
Version: 0.2.1
Summary: edx-ora2
Home-page: http://github.com/uuuuv/edx-ora2
Author: uuuuv
Author-email: uuuuv@github.com
License: AGPL
Platform: UNKNOWN
Classifier: Development Status :: 5 - Production/Stable
Classifier: Framework :: Django :: 3.2
Classifier: Framework :: Django :: 4.2
Classifier: Intended Audience :: Developers
Classifier: License :: OSI Approved :: GNU Affero General Public License v3
Classifier: Operating System :: OS Independent
Classifier: Programming Language :: Python :: 3
Classifier: Programming Language :: Python :: 3.8
License-File: LICENSE
Requires-Dist: Xblock
Requires-Dist: bleach (>=6.0.0)
Requires-Dist: boto3
Requires-Dist: defusedxml
Requires-Dist: django
Requires-Dist: django-model-utils
Requires-Dist: django-simple-history
Requires-Dist: djangorestframework
Requires-Dist: edx-django-utils
Requires-Dist: edx-i18n-tools
Requires-Dist: edx-opaque-keys
Requires-Dist: edx-submissions
Requires-Dist: edx-toggles
Requires-Dist: html5lib
Requires-Dist: jsonfield
Requires-Dist: lazy
Requires-Dist: loremipsum
Requires-Dist: lxml
Requires-Dist: path.py
Requires-Dist: python-dateutil
Requires-Dist: python-swiftclient
Requires-Dist: pytz
Requires-Dist: voluptuous
